m3wal/__init__.py
m3wal/m3wal.py
m3wal/templates/colors-alacritty.toml.template
m3wal/templates/colors-nvim.lua.template
m3wal/templates/colors-tty.sh.template
m3wal/templates/colors-waybar.css.template
m3wal/templates/colors.Xresources.template
m3wal/templates/colors.css.template
m3wal/templates/colors.hs.template
m3wal/templates/colors.json.template
m3wal/templates/colors.scss.template
m3wal/templates/colors.sh.template
m3wal/templates/colors.template
m3wal/templates/colors.yml.template
m3wal/templates/dunst-config.template
m3wal/templates/gtk.3.20.template
m3wal/templates/gtk.css.template
m3wal/templates/gtkrc.template
m3wal/templates/kdeglobals.template
m3wal/templates/kitty.conf.template
m3wal/templates/polybar-config.template
m3wal/templates/qt5ct.conf.template
m3wal/templates/qt6ct.conf.template
m3wal/templates/rmpc.ron.template
m3wal/templates/rofi.rasi.template
m3wal/templates/sequences.template
m3wal/templates/zathurarc.template
m3wal-1.1.9.dist-info/licenses/LICENSE.txt
m3wal-1.1.9.dist-info/METADATA
m3wal-1.1.9.dist-info/WHEEL
m3wal-1.1.9.dist-info/entry_points.txt
m3wal-1.1.9.dist-info/top_level.txt
m3wal-1.1.9.dist-info/RECORD
