Metadata-Version: 2.4
Name: m3wal
Version: 1.1.9
Summary: Material 3 wallpaper-based color scheme generator for Linux desktop theming
Home-page: https://github.com/MDiaznf23/m3wal
Author: Diaz
License: MIT
Project-URL: Bug Tracker, https://github.com/MDiaznf23/m3wal/issues
Project-URL: Documentation, https://github.com/MDiaznf23/m3wal#readme
Project-URL: Source Code, https://github.com/MDiaznf23/m3wal
Keywords: material-design,material3,color-scheme,wallpaper,theming,rice,ricing,linux,desktop,gtk,customization
Classifier: Development Status :: 4 - Beta
Classifier: Intended Audience :: Developers
Classifier: Intended Audience :: End Users/Desktop
Classifier: Topic :: Desktop Environment
Classifier: Topic :: System :: Installation/Setup
Classifier: Topic :: Utilities
Classifier: Programming Language :: Python :: 3
Classifier: Programming Language :: Python :: 3.7
Classifier: Programming Language :: Python :: 3.8
Classifier: Programming Language :: Python :: 3.9
Classifier: Programming Language :: Python :: 3.10
Classifier: Programming Language :: Python :: 3.11
Classifier: Programming Language :: Python :: 3.12
Classifier: License :: OSI Approved :: MIT License
Classifier: Operating System :: POSIX :: Linux
Classifier: Environment :: Console
Requires-Python: >=3.7
License-File: LICENSE.txt
Requires-Dist: material-color-utilities
Requires-Dist: Pillow
Dynamic: author
Dynamic: classifier
Dynamic: description
Dynamic: description-content-type
Dynamic: home-page
Dynamic: keywords
Dynamic: license
Dynamic: license-file
Dynamic: project-url
Dynamic: requires-dist
Dynamic: requires-python
Dynamic: summary
